{"cameraMode":{"drawMode":0,"name":"Shaded","section":"Shading Mode"},"sceneLighting":false,"audioPlay":false,"sceneViewState":{"m_AlwaysRefresh":false,"showFog":true,"showSkybox":false,"showFlares":true,"showImageEffects":true,"showParticleSystems":true,"showVisualEffectGraphs":true,"m_FxEnabled":true},"in2DMode":false,"pivot":{"x":-2.4365744590759279,"y":0.1874198466539383,"z":4.562654972076416},"rotation":{"x":0.023300403729081155,"y":0.9667903184890747,"z":-0.09544944763183594,"w":0.23597799241542817},"size":0.0023846947588026525,"orthographic":false}